go2rtc_client/__init__.py
go2rtc_client/exceptions.py
go2rtc_client/models.py
go2rtc_client/py.typed
go2rtc_client/rest.py
go2rtc_client/ws/__init__.py
go2rtc_client/ws/client.py
go2rtc_client/ws/messages.py
go2rtc_client-0.4.0.dist-info/METADATA
go2rtc_client-0.4.0.dist-info/WHEEL
go2rtc_client-0.4.0.dist-info/licenses/LICENSE
go2rtc_client-0.4.0.dist-info/RECORD
