Metadata-Version: 2.4
Name: go2rtc-client
Version: 0.4.0
Summary: Python client for go2rtc
Project-URL: Homepage, https://pypi.org/project/go2rtc-client
Project-URL: Source Code, https://github.com/home-assistant-libs/python-go2rtc-client
Project-URL: Bug Reports, https://github.com/home-assistant-libs/python-go2rtc-client/issues
Author-email: Robert Resch <robert@resch.dev>
License: Apache-2.0
License-File: LICENSE
Keywords: go2rtc,stream,webrtc
Classifier: Development Status :: 3 - Alpha
Classifier: Intended Audience :: Developers
Classifier: Programming Language :: Python :: 3.12
Requires-Python: >=3.12.0
Requires-Dist: aiohttp~=3.10
Requires-Dist: awesomeversion>=24.6
Requires-Dist: mashumaro~=3.13
Requires-Dist: orjson~=3.10
Requires-Dist: webrtc-models~=0.1
